web_oto_dev_sdk/__init__.py
web_oto_dev_sdk/sdk.py
web_oto_dev_sdk/sdk_async.py
web_oto_dev_sdk/sdk_wrapper.py
web_oto_dev_sdk/hooks/__init__.py
web_oto_dev_sdk/hooks/hook.py
web_oto_dev_sdk/models/__init__.py
web_oto_dev_sdk/models/form_field.py
web_oto_dev_sdk/models/formula.py
web_oto_dev_sdk/models/http_validation_error.py
web_oto_dev_sdk/models/meaning.py
web_oto_dev_sdk/models/menu_item.py
web_oto_dev_sdk/models/project_info.py
web_oto_dev_sdk/models/property.py
web_oto_dev_sdk/models/validation_error.py
web_oto_dev_sdk/models/value.py
web_oto_dev_sdk/models/utils/__init__.py
web_oto_dev_sdk/models/utils/base_model.py
web_oto_dev_sdk/models/utils/cast_models.py
web_oto_dev_sdk/models/utils/json_map.py
web_oto_dev_sdk/models/utils/one_of_base_model.py
web_oto_dev_sdk/models/utils/sentinel.py
web_oto_dev_sdk/net/__init__.py
web_oto_dev_sdk/net/environment/__init__.py
web_oto_dev_sdk/net/environment/environment.py
web_oto_dev_sdk/net/headers/__init__.py
web_oto_dev_sdk/net/headers/api_key_auth.py
web_oto_dev_sdk/net/headers/base_header.py
web_oto_dev_sdk/net/request_chain/__init__.py
web_oto_dev_sdk/net/request_chain/request_chain.py
web_oto_dev_sdk/net/request_chain/handlers/__init__.py
web_oto_dev_sdk/net/request_chain/handlers/base_handler.py
web_oto_dev_sdk/net/request_chain/handlers/hook_handler.py
web_oto_dev_sdk/net/request_chain/handlers/http_handler.py
web_oto_dev_sdk/net/request_chain/handlers/retry_handler.py
web_oto_dev_sdk/net/transport/__init__.py
web_oto_dev_sdk/net/transport/api_error.py
web_oto_dev_sdk/net/transport/request.py
web_oto_dev_sdk/net/transport/request_error.py
web_oto_dev_sdk/net/transport/response.py
web_oto_dev_sdk/net/transport/serializer.py
web_oto_dev_sdk/net/transport/utils.py
web_oto_dev_sdk/services/__init__.py
web_oto_dev_sdk/services/admin.py
web_oto_dev_sdk/services/context.py
web_oto_dev_sdk/services/crm.py
web_oto_dev_sdk/services/crm_deals.py
web_oto_dev_sdk/services/formulas.py
web_oto_dev_sdk/services/layouts.py
web_oto_dev_sdk-1.0.16.dist-info/licenses/LICENSE
web_oto_dev_sdk-1.0.16.dist-info/METADATA
web_oto_dev_sdk-1.0.16.dist-info/WHEEL
web_oto_dev_sdk-1.0.16.dist-info/top_level.txt
web_oto_dev_sdk-1.0.16.dist-info/RECORD
