Metadata-Version: 2.4
Name: web_oto_dev_sdk
Version: 1.0.16
Summary: API v1 for web.oto.dev service
License: MIT
Requires-Python: >=3.9
License-File: LICENSE
Requires-Dist: requests>=2.31.0
Dynamic: license-file
